{
  "name": "siyuan-plugin-ticktick-task-center",
  "author": "Yong2Sheng",
  "url": "https://github.com/Yong2Sheng/siyuan-plugin-ticktick-task-center",
  "version": "0.1.0",
  "minAppVersion": "3.7.0",
  "disabledInPublish": true,
  "backends": [
    "windows",
    "linux",
    "darwin"
  ],
  "frontends": [
    "desktop",
    "desktop-window"
  ],
  "displayName": {
    "default": "TickTick Task Center",
    "zh-CN": "滴答任务中心"
  },
  "description": {
    "default": "Manage TickTick task cards and a dynamic task center in SiYuan.",
    "zh-CN": "在思源中管理滴答清单任务卡片与动态任务中心。"
  },
  "readme": {
    "default": "README.md",
    "zh-CN": "README.zh-CN.md"
  },
  "funding": {
    "openCollective": "",
    "patreon": "",
    "github": "",
    "custom": []
  },
  "keywords": [
    "ticktick",
    "task",
    "task-center",
    "滴答清单",
    "任务中心"
  ]
}
